src/__init__.py
src/commands.py
src/main.py
create_ds-0.0.1.dist-info/entry_points.txt
create_ds-0.0.1.dist-info/licenses/LICENSE
create_ds-0.0.1.dist-info/WHEEL
create_ds-0.0.1.dist-info/METADATA
create_ds-0.0.1.dist-info/RECORD
