Metadata-Version: 2.4
Name: create-ds
Version: 0.0.1
Summary: Python tool to create folders and files structure for DataScience project
Keywords: data science,project structure,automation
Author-email: Bartek <szymik.bartek@gmail.com>
Requires-Python: >=3.13
License-Expression: Beerware
License-File: LICENSE
Requires-Dist: rich>=13.9.4
Requires-Dist: typer>=0.15.2
Project-URL: Home, https://github.com/BartekSzymik/create-ds-projects
